browsergym_weblinx/__init__.py
browsergym_weblinx/version.py
browsergym_weblinx-0.0.1.dev0.dist-info/METADATA
browsergym_weblinx-0.0.1.dev0.dist-info/WHEEL
browsergym_weblinx-0.0.1.dev0.dist-info/top_level.txt
browsergym_weblinx-0.0.1.dev0.dist-info/RECORD
