Metadata-Version: 2.1
Name: browsergym-weblinx
Version: 0.0.1.dev0
Summary: BrowserGym integration for the WebLINX benchmark
Home-page: https://github.com/McGill-NLP/browsergym_weblinx
Author: McGill NLP
Author-email: weblinx@googlegroups.com
Classifier: Programming Language :: Python :: 3
Requires-Python: >=3.10
Requires-Dist: tqdm
Requires-Dist: huggingface-hub
Requires-Dist: numpy
Requires-Dist: weblinx[eval]>=0.3.2
Requires-Dist: datasets
Requires-Dist: Pillow
Requires-Dist: playwright
Requires-Dist: browsergym
Requires-Dist: lxml
Requires-Dist: gymnasium
Provides-Extra: all
Requires-Dist: black; extra == "all"
Requires-Dist: wheel; extra == "all"
Provides-Extra: dev
Requires-Dist: black; extra == "dev"
Requires-Dist: wheel; extra == "dev"
